Metadata-Version: 2.1
Name: ILOVEHYPIXEL
Version: 0.0.1
Summary: This package tells you to play Hypixel
Author: My Name
Author-email: marmazeev.dima@gmail.com
